cofactr/__init__.py
cofactr/graph.py
cofactr/helpers.py
cofactr/schema/__init__.py
cofactr/schema/flagship/__init__.py
cofactr/schema/flagship/offer.py
cofactr/schema/flagship/order.py
cofactr/schema/flagship/part.py
cofactr/schema/flagship/seller.py
cofactr/schema/flagship_alts_v0/__init__.py
cofactr/schema/flagship_alts_v0/part.py
cofactr/schema/flagship_cache_v0/__init__.py
cofactr/schema/flagship_cache_v0/part.py
cofactr/schema/flagship_cache_v1/__init__.py
cofactr/schema/flagship_cache_v1/part.py
cofactr/schema/flagship_cache_v2/__init__.py
cofactr/schema/flagship_cache_v2/part.py
cofactr/schema/flagship_cache_v3/__init__.py
cofactr/schema/flagship_cache_v3/part.py
cofactr/schema/flagship_cache_v4/__init__.py
cofactr/schema/flagship_cache_v4/part.py
cofactr/schema/flagship_cache_v5/__init__.py
cofactr/schema/flagship_cache_v5/part.py
cofactr/schema/flagship_cache_v6/__init__.py
cofactr/schema/flagship_cache_v6/part.py
cofactr/schema/flagship_v2/__init__.py
cofactr/schema/flagship_v2/offer.py
cofactr/schema/flagship_v2/order.py
cofactr/schema/flagship_v2/part.py
cofactr/schema/flagship_v2/seller.py
cofactr/schema/flagship_v3/__init__.py
cofactr/schema/flagship_v3/offer.py
cofactr/schema/flagship_v3/part.py
cofactr/schema/flagship_v3/seller.py
cofactr/schema/flagship_v4/__init__.py
cofactr/schema/flagship_v4/offer.py
cofactr/schema/flagship_v4/part.py
cofactr/schema/flagship_v4/seller.py
cofactr/schema/flagship_v5/__init__.py
cofactr/schema/flagship_v5/offer.py
cofactr/schema/flagship_v5/part.py
cofactr/schema/flagship_v5/seller.py
cofactr/schema/flagship_v6/__init__.py
cofactr/schema/flagship_v6/offer.py
cofactr/schema/flagship_v6/part.py
cofactr/schema/flagship_v6/seller.py
cofactr/schema/flagship_v7/__init__.py
cofactr/schema/flagship_v7/offer.py
cofactr/schema/flagship_v7/part.py
cofactr/schema/flagship_v7/seller.py
cofactr/schema/flagship_v8/__init__.py
cofactr/schema/flagship_v8/offer.py
cofactr/schema/flagship_v8/seller.py
cofactr-5.38.1.dist-info/LICENSE.txt
cofactr-5.38.1.dist-info/METADATA
cofactr-5.38.1.dist-info/WHEEL
cofactr-5.38.1.dist-info/RECORD
