Metadata-Version: 2.1
Name: cofactr
Version: 5.38.1
Summary: Client library for accessing Cofactr data.
Home-page: https://github.com/Cofactr/cofactr-client
License: MIT
Keywords: cofactr
Author: Joseph Sayad
Author-email: joseph@cofactr.com
Requires-Python: >=3.10,<4.0
Classifier: License :: OSI Approved :: MIT License
Classifier: Programming Language :: Python :: 3
Classifier: Programming Language :: Python :: 3.10
Classifier: Programming Language :: Python :: 3.11
Classifier: Programming Language :: Python :: 3.12
Classifier: Programming Language :: Python :: 3.9
Requires-Dist: httpx (>=0.23.0,<1.0.0)
Requires-Dist: more-itertools (>=9.0.0,<10.0.0)
Requires-Dist: tenacity (>=8.1.0,<9.0.0)
Requires-Dist: typing-extensions (>=4.5.0,<5.0.0)
Project-URL: Repository, https://github.com/Cofactr/cofactr-client
